{
	"parameterSets": {
		"p1611": {
			"size_atoms": "[9, 9, 9]"
		},
		"p1615": {
			"size_atoms": "[18, 27, 9]"
		},
		"p1617": {
			"size_atoms": "[12, 24, 12]"
		},
		"p1618": {
			"size_atoms": "[12, 24, 12]",
			"floor_thickness": "3",
			"inner_flange_depth": "22.2",
			"wall_inset": "0",
			"wall_thickness": "3"
		},
		"p1623": {
			"size_atoms": "[12, 24, 9]",
			"floor_thickness": "3",
			"inner_flange_depth": "22.2",
			"wall_inset": "0",
			"wall_thickness": "3"
		},
		"p2167": {
			"floor_thickness": "0",
			"inner_flange_depth": "22.2",
			"port_config": "P2167Like",
			"size_atoms": "[27, 18, 3]",
			"wall_inset": "0",
			"wall_thickness": "3"
		},
		"p2174": {
			"floor_thickness": "0",
			"inner_flange_depth": "19",
			"inner_flange_slope": "0.66",
			"outer_flange_slope": "0.66",
			"port_config": "P2167Like",
			"size_atoms": "[27, 18, 3]",
			"wall_inset": "0",
			"wall_thickness": "3"
		}
	},
	"parameterSets": "",
	"fileFormatVersion": "1"
}
